LICENSE.txt
MANIFEST.in
README.txt
setup.py
pcart_tires_theme/__init__.py
pcart_tires_theme/context_processors.py
pcart_tires_theme/settings.py
pcart_tires_theme/urls.py
pcart_tires_theme/utils.py
pcart_tires_theme/views.py
pcart_tires_theme.egg-info/PKG-INFO
pcart_tires_theme.egg-info/SOURCES.txt
pcart_tires_theme.egg-info/dependency_links.txt
pcart_tires_theme.egg-info/not-zip-safe
pcart_tires_theme.egg-info/requires.txt
pcart_tires_theme.egg-info/top_level.txt
pcart_tires_theme/locale/ru/LC_MESSAGES/django.mo
pcart_tires_theme/locale/ru/LC_MESSAGES/django.po
pcart_tires_theme/locale/uk/LC_MESSAGES/django.mo
pcart_tires_theme/locale/uk/LC_MESSAGES/django.po
pcart_tires_theme/static/assets/FontAwesome.otf
pcart_tires_theme/static/assets/all.gif
pcart_tires_theme/static/assets/blank.gif
pcart_tires_theme/static/assets/bootstrap.css
pcart_tires_theme/static/assets/bx_loader.gif
pcart_tires_theme/static/assets/cc-amex.png
pcart_tires_theme/static/assets/cc-cirrus.png
pcart_tires_theme/static/assets/cc-discover.png
pcart_tires_theme/static/assets/cc-google.png
pcart_tires_theme/static/assets/cc-maestro.png
pcart_tires_theme/static/assets/cc-mastercard.png
pcart_tires_theme/static/assets/cc-paypal.png
pcart_tires_theme/static/assets/cc-visa.png
pcart_tires_theme/static/assets/custom_showcase1_img.png
pcart_tires_theme/static/assets/custom_showcase2_img.png
pcart_tires_theme/static/assets/custom_showcase3_img.png
pcart_tires_theme/static/assets/custom_showcase4_img.png
pcart_tires_theme/static/assets/empty.480x480.png
pcart_tires_theme/static/assets/favicon.ico
pcart_tires_theme/static/assets/fontawesome-webfont.eot
pcart_tires_theme/static/assets/fontawesome-webfont.svg
pcart_tires_theme/static/assets/fontawesome-webfont.ttf
pcart_tires_theme/static/assets/fontawesome-webfont.woff
pcart_tires_theme/static/assets/homepage_brands1_img.png
pcart_tires_theme/static/assets/homepage_brands2_img.png
pcart_tires_theme/static/assets/homepage_brands3_img.png
pcart_tires_theme/static/assets/homepage_brands4_img.png
pcart_tires_theme/static/assets/homepage_brands5_img.png
pcart_tires_theme/static/assets/homepage_brands6_img.png
pcart_tires_theme/static/assets/homepage_info_bg.jpg
